setup.py
robots_scanner/__init__.py
robots_scanner/scanner.py
robots_scanner.egg-info/PKG-INFO
robots_scanner.egg-info/SOURCES.txt
robots_scanner.egg-info/dependency_links.txt
robots_scanner.egg-info/top_level.txt
tests/__init__.py
tests/tests.py