Metadata-Version: 1.0
Name: robots-scanner
Version: 0.1.2
Summary: robots.txt scanner
Home-page: UNKNOWN
Author: Yeuk Hon Wong
Author-email: yeukhon@mozilla.com
License: UNKNOWN
Platform: UNKNOWN
Classifier: Programming Language :: Python :: 2.6
Classifier: Programming Language :: Python :: 2.7
Classifier: Topic :: Internet
Classifier: Topic :: Security
